{
  "nodes": {
    "H0": {
      "type": "hypothesis",
      "text": "Producer is the type of organism that helps return nutrients from dead plants and animals to the soil.",
      "strength": 0.5
    },
    "H1": {
      "type": "hypothesis",
      "text": "Prey helps return nutrients from dead plants and animals to the soil.",
      "strength": 0.5
    },
    "H2": {
      "type": "hypothesis",
      "text": "Predators are organisms that help return nutrients from dead plants and animals to the soil.",
      "strength": 0.5
    },
    "H3": {
      "type": "hypothesis",
      "text": "Decomposer is an organism that helps return nutrients from dead plants and animals to the soil.",
      "strength": 0.749902562007873
    },
    "A4": {
      "type": "argument",
      "text": "Decomposers are organisms that break down dead organisms and release the nutrients from the dead matter into the environment around them.",
      "strength": 0.5
    },
    "A5": {
      "type": "argument",
      "text": "They must therefore rely on decomposers to free up nutrients from dead matter that they can then absorb.",
      "strength": 0.5
    }
  },
  "edges": [
    {
      "source": "A4",
      "target": "H3",
      "relation": "support"
    },
    {
      "source": "A5",
      "target": "H3",
      "relation": "support"
    }
  ]
}