{
  "nodes": {
    "H0": {
      "type": "hypothesis",
      "text": "Mass is represented by the 20 mL increase in water level in the graduated cylinder when a student places a rock in it.",
      "strength": 0.5
    },
    "H1": {
      "type": "hypothesis",
      "text": "Volume is the 20 mL increase in water level that occurs when a student places a rock in a graduated cylinder containing water.",
      "strength": 0.5999031730402274
    },
    "H2": {
      "type": "hypothesis",
      "text": "Solubility is the 20 mL increase in the water level in the graduated cylinder when a student places a rock in it.",
      "strength": 0.5
    },
    "H3": {
      "type": "hypothesis",
      "text": "Temperature is what the 20 mL increase in water level represents when a student placed a rock in a graduated cylinder containing water.",
      "strength": 0.5
    },
    "A4": {
      "type": "argument",
      "text": "The water volume difference is the volume of the object.",
      "strength": 0.5
    }
  },
  "edges": [
    {
      "source": "A4",
      "target": "H1",
      "relation": "support"
    }
  ]
}