{
  "nodes": {
    "H0": {
      "type": "hypothesis",
      "text": "Absorbed from the soil through the roots is how plants get water and minerals.",
      "strength": 0.749902562007873
    },
    "H1": {
      "type": "hypothesis",
      "text": "Absorption from the soil through the stem allows plants to obtain water and minerals.",
      "strength": 0.5
    },
    "H2": {
      "type": "hypothesis",
      "text": "Water and minerals are absorbed from the air through the flowers.",
      "strength": 0.5
    },
    "H3": {
      "type": "hypothesis",
      "text": "Absorbed from the air through the leaves is how plants get water and minerals.",
      "strength": 0.5
    },
    "A4": {
      "type": "argument",
      "text": "Roots perform several essential and specialised roles that support plant growth, development and survival. Their primary functions are anchorage, uptake (absorption) of water and dissolved minerals, and conduction of these resources to the shoot.",
      "strength": 0.5
    },
    "A5": {
      "type": "argument",
      "text": "Absorption of water and mineral nutrients. Root epidermal cells and root hairs take up soil water and dissolved ions; these are then conducted to the shoot via the xylem.",
      "strength": 0.5
    }
  },
  "edges": [
    {
      "source": "A4",
      "target": "H0",
      "relation": "support"
    },
    {
      "source": "A5",
      "target": "H0",
      "relation": "support"
    }
  ]
}