{
  "nodes": {
    "H0": {
      "type": "hypothesis",
      "text": "Mass is what 12.0 grams represents.",
      "strength": 0.5999031730402274
    },
    "H1": {
      "type": "hypothesis",
      "text": "Volume represents 12.0 grams.",
      "strength": 0.5
    },
    "H2": {
      "type": "hypothesis",
      "text": "Speed is what 12.0 grams represents.",
      "strength": 0.5
    },
    "H3": {
      "type": "hypothesis",
      "text": "Force is what 12.0 grams represents.",
      "strength": 0.5
    },
    "A4": {
      "type": "argument",
      "text": "The gram (originally gramme; SI unit symbol g) is a unit of mass in the International System of Units (SI) equal to one thousandth of a kilogram.",
      "strength": 0.5
    }
  },
  "edges": [
    {
      "source": "A4",
      "target": "H0",
      "relation": "support"
    }
  ]
}