{
  "nodes": {
    "H0": {
      "type": "hypothesis",
      "text": "Which famous fishing town of east Scotland lies roughly half-way between Montrose and Dundee. Carnoustie",
      "strength": 0.5
    },
    "H1": {
      "type": "hypothesis",
      "text": "Which famous fishing town of east Scotland lies roughly half-way between Montrose and Dundee. Monifieth",
      "strength": 0.5
    },
    "H2": {
      "type": "hypothesis",
      "text": "Which famous fishing town of east Scotland lies roughly half-way between Montrose and Dundee. Broughty Ferry",
      "strength": 0.5
    },
    "H3": {
      "type": "hypothesis",
      "text": "Which famous fishing town of east Scotland lies roughly half-way between Montrose and Dundee. Arbroth",
      "strength": 0.5
    }
  },
  "edges": []
}