{
  "nodes": {
    "H0": {
      "type": "hypothesis",
      "text": "What is the fictional location of the tv soap ‘Eastenders’. Albertville",
      "strength": 0.5
    },
    "H1": {
      "type": "hypothesis",
      "text": "What is the fictional location of the tv soap ‘Eastenders’. Brickston",
      "strength": 0.5
    },
    "H2": {
      "type": "hypothesis",
      "text": "What is the fictional location of the tv soap ‘Eastenders’. Camden",
      "strength": 0.5
    },
    "H3": {
      "type": "hypothesis",
      "text": "What is the fictional location of the tv soap ‘Eastenders’. WALFORD",
      "strength": 0.5
    }
  },
  "edges": []
}