{
  "nodes": {
    "H0": {
      "type": "hypothesis",
      "text": "Marie Antoinette, Queen of France and Navarre, was born in which country. France",
      "strength": 0.4000911881966091
    },
    "H1": {
      "type": "hypothesis",
      "text": "Marie Antoinette, Queen of France and Navarre, was born in which country. Germany",
      "strength": 0.4000911881966091
    },
    "H2": {
      "type": "hypothesis",
      "text": "Marie Antoinette, Queen of France and Navarre, was born in which country. Italy",
      "strength": 0.5
    },
    "H3": {
      "type": "hypothesis",
      "text": "Marie Antoinette, Queen of France and Navarre, was born in which country. Ostria",
      "strength": 0.5
    },
    "A4": {
      "type": "argument",
      "text": "Born an archduchess of Austria",
      "strength": 0.5
    },
    "A5": {
      "type": "argument",
      "text": "youngest daughter of Empress Maria Theresa and Emperor Francis I of the Holy Roman Empire",
      "strength": 0.5
    }
  },
  "edges": [
    {
      "source": "A4",
      "target": "H0",
      "relation": "attack"
    },
    {
      "source": "A5",
      "target": "H1",
      "relation": "attack"
    }
  ]
}