{
  "nodes": {
    "H0": {
      "type": "hypothesis",
      "text": "Michelangelo Merisi (or Amerighi) is the birth name of which artist. Michelangelo Buonarroti",
      "strength": 0.5
    },
    "H1": {
      "type": "hypothesis",
      "text": "Michelangelo Merisi (or Amerighi) is the birth name of which artist. Tintoretto",
      "strength": 0.5
    },
    "H2": {
      "type": "hypothesis",
      "text": "Michelangelo Merisi (or Amerighi) is the birth name of which artist. Gian Lorenzo Bernini",
      "strength": 0.5
    },
    "H3": {
      "type": "hypothesis",
      "text": "Michelangelo Merisi (or Amerighi) is the birth name of which artist. Caravage",
      "strength": 0.5
    }
  },
  "edges": []
}