{
  "nodes": {
    "H0": {
      "type": "hypothesis",
      "text": "In which decade did Coates compose 'The Dam Busters March'. 1920's",
      "strength": 0.5
    },
    "H1": {
      "type": "hypothesis",
      "text": "In which decade did Coates compose 'The Dam Busters March'. 1930's",
      "strength": 0.5
    },
    "H2": {
      "type": "hypothesis",
      "text": "In which decade did Coates compose 'The Dam Busters March'. 1940's",
      "strength": 0.5
    },
    "H3": {
      "type": "hypothesis",
      "text": "In which decade did Coates compose 'The Dam Busters March'. 50's",
      "strength": 0.5999031730402274
    },
    "A4": {
      "type": "argument",
      "text": "A march he had recently completed was found to fit well with the heroic subject and was thus submitted.",
      "strength": 0.5
    }
  },
  "edges": [
    {
      "source": "A4",
      "target": "H3",
      "relation": "support"
    }
  ]
}