{
  "nodes": {
    "H0": {
      "type": "hypothesis",
      "text": "\"Bellis perennis\" is the Latin name for which flower. Buttercup",
      "strength": 0.5
    },
    "H1": {
      "type": "hypothesis",
      "text": "\"Bellis perennis\" is the Latin name for which flower. Violet",
      "strength": 0.5
    },
    "H2": {
      "type": "hypothesis",
      "text": "\"Bellis perennis\" is the Latin name for which flower. Primrose",
      "strength": 0.5
    },
    "H3": {
      "type": "hypothesis",
      "text": "\"Bellis perennis\" is the Latin name for which flower. Daisy",
      "strength": 0.5
    }
  },
  "edges": []
}