{
  "nodes": {
    "H0": {
      "type": "hypothesis",
      "text": "Ikarus was the codename for the proposed German invasion of which country. United Kingdom",
      "strength": 0.25008138705228505
    },
    "H1": {
      "type": "hypothesis",
      "text": "Ikarus was the codename for the proposed German invasion of which country. Soviet Union",
      "strength": 0.5
    },
    "H2": {
      "type": "hypothesis",
      "text": "Ikarus was the codename for the proposed German invasion of which country. Poland",
      "strength": 0.5
    },
    "H3": {
      "type": "hypothesis",
      "text": "Ikarus was the codename for the proposed German invasion of which country. Hyui",
      "strength": 0.5
    },
    "A4": {
      "type": "argument",
      "text": "Operation Ikarus was a German plan to invade Iceland, not the United Kingdom.",
      "strength": 0.5
    },
    "A5": {
      "type": "argument",
      "text": "The British occupied Iceland to prevent a German invasion of the island.",
      "strength": 0.5
    }
  },
  "edges": [
    {
      "source": "A4",
      "target": "H0",
      "relation": "attack"
    },
    {
      "source": "A5",
      "target": "H0",
      "relation": "attack"
    }
  ]
}