{
  "nodes": {
    "H0": {
      "type": "hypothesis",
      "text": "\"Giovedi\" is the Italian word for which day of the week. Monday",
      "strength": 0.5
    },
    "H1": {
      "type": "hypothesis",
      "text": "\"Giovedi\" is the Italian word for which day of the week. Tuesday",
      "strength": 0.5
    },
    "H2": {
      "type": "hypothesis",
      "text": "\"Giovedi\" is the Italian word for which day of the week. Wednesday",
      "strength": 0.5
    },
    "H3": {
      "type": "hypothesis",
      "text": "\"Giovedi\" is the Italian word for which day of the week. Thurs.",
      "strength": 0.5
    }
  },
  "edges": []
}