{
  "nodes": {
    "H0": {
      "type": "hypothesis",
      "text": "Whose third symphony is also called his ‘organ symphony’. Beethoven",
      "strength": 0.5
    },
    "H1": {
      "type": "hypothesis",
      "text": "Whose third symphony is also called his ‘organ symphony’. Brahms",
      "strength": 0.5
    },
    "H2": {
      "type": "hypothesis",
      "text": "Whose third symphony is also called his ‘organ symphony’. Bruckner",
      "strength": 0.5
    },
    "H3": {
      "type": "hypothesis",
      "text": "Whose third symphony is also called his ‘organ symphony’. Saint Saen",
      "strength": 0.749902562007873
    },
    "A4": {
      "type": "argument",
      "text": "The Symphony No. 3 in C minor, Op. 78, was completed by Camille Saint-Saëns in 1886 and is popularly known as the Organ Symphony",
      "strength": 0.5
    },
    "A5": {
      "type": "argument",
      "text": "The composer inscribed it as: Symphonie No. 3 'avec orgue' (with organ)",
      "strength": 0.5
    }
  },
  "edges": [
    {
      "source": "A4",
      "target": "H3",
      "relation": "support"
    },
    {
      "source": "A5",
      "target": "H3",
      "relation": "support"
    }
  ]
}