{
  "nodes": {
    "H0": {
      "type": "hypothesis",
      "text": "Which English town/city did the Romans call Dubris. Southampton",
      "strength": 0.5
    },
    "H1": {
      "type": "hypothesis",
      "text": "Which English town/city did the Romans call Dubris. Portsmouth",
      "strength": 0.5
    },
    "H2": {
      "type": "hypothesis",
      "text": "Which English town/city did the Romans call Dubris. Exeter",
      "strength": 0.5
    },
    "H3": {
      "type": "hypothesis",
      "text": "Which English town/city did the Romans call Dubris. Dover",
      "strength": 0.5999031730402274
    },
    "A4": {
      "type": "argument",
      "text": "During the Roman period, the area became part of the Roman communications network. It was connected by road to Canterbury and Watling Street and it became Portus Dubris, a fortified port.",
      "strength": 0.5
    }
  },
  "edges": [
    {
      "source": "A4",
      "target": "H3",
      "relation": "support"
    }
  ]
}