{
  "nodes": {
    "H0": {
      "type": "hypothesis",
      "text": "What is the word for the process of using strong acid or mordant to cut into the unprotected parts of a metal surface to create a design in intaglio in the metal. Engraver",
      "strength": 0.5
    },
    "H1": {
      "type": "hypothesis",
      "text": "What is the word for the process of using strong acid or mordant to cut into the unprotected parts of a metal surface to create a design in intaglio in the metal. Acidographer",
      "strength": 0.5
    },
    "H2": {
      "type": "hypothesis",
      "text": "What is the word for the process of using strong acid or mordant to cut into the unprotected parts of a metal surface to create a design in intaglio in the metal. Intagliator",
      "strength": 0.5
    },
    "H3": {
      "type": "hypothesis",
      "text": "What is the word for the process of using strong acid or mordant to cut into the unprotected parts of a metal surface to create a design in intaglio in the metal. Etcher",
      "strength": 0.4999026003661934
    },
    "A4": {
      "type": "argument",
      "text": "Etching is traditionally the process of using strong acid or mordant to cut into the unprotected parts of a metal surface to create a design in intaglio (incised) in the metal.",
      "strength": 0.5
    },
    "A5": {
      "type": "argument",
      "text": "The etching process is known as biting (see also spit-biting below).",
      "strength": 0.5
    },
    "A6": {
      "type": "argument",
      "text": "Carrington, Fitzroy. Prints and their makers: essays on engravers and etchers old and modern.",
      "strength": 0.5
    },
    "A7": {
      "type": "argument",
      "text": "Etching from the MMA Timeline of Art History",
      "strength": 0.5
    }
  },
  "edges": [
    {
      "source": "A4",
      "target": "H3",
      "relation": "attack"
    },
    {
      "source": "A5",
      "target": "H3",
      "relation": "attack"
    },
    {
      "source": "A6",
      "target": "H3",
      "relation": "support"
    },
    {
      "source": "A7",
      "target": "H3",
      "relation": "support"
    }
  ]
}