{
  "nodes": {
    "H0": {
      "type": "hypothesis",
      "text": "What is the capital of Guyana. Georgetown",
      "strength": 0.749902562007873
    },
    "H1": {
      "type": "hypothesis",
      "text": "What is the capital of Guyana. New Amsterdam",
      "strength": 0.5
    },
    "H2": {
      "type": "hypothesis",
      "text": "What is the capital of Guyana. Linden",
      "strength": 0.5
    },
    "H3": {
      "type": "hypothesis",
      "text": "What is the capital of Guyana. G-town",
      "strength": 0.5
    },
    "A4": {
      "type": "argument",
      "text": "Georgetown is the capital and largest city of Guyana.",
      "strength": 0.5
    },
    "A5": {
      "type": "argument",
      "text": "All executive departments of Guyana's government are located in the city, including Parliament Building, Guyana's Legislative Building and the Court of Appeals, Guyana's highest judicial court.",
      "strength": 0.5
    }
  },
  "edges": [
    {
      "source": "A4",
      "target": "H0",
      "relation": "support"
    },
    {
      "source": "A5",
      "target": "H0",
      "relation": "support"
    }
  ]
}