{
  "nodes": {
    "H0": {
      "type": "hypothesis",
      "text": "From which film did the Oscar winning song `Up Where We Belong' come. An Officer and a Gentleman",
      "strength": 0.5
    },
    "H1": {
      "type": "hypothesis",
      "text": "From which film did the Oscar winning song `Up Where We Belong' come. Top Gun",
      "strength": 0.5
    },
    "H2": {
      "type": "hypothesis",
      "text": "From which film did the Oscar winning song `Up Where We Belong' come. Dirty Dancing",
      "strength": 0.5
    },
    "H3": {
      "type": "hypothesis",
      "text": "From which film did the Oscar winning song `Up Where We Belong' come. Zack Mayo",
      "strength": 0.5
    }
  },
  "edges": []
}