{
  "nodes": {
    "H0": {
      "type": "hypothesis",
      "text": "If you were in Japan eating edamame, what would you be eating. Boiled Peas",
      "strength": 0.5
    },
    "H1": {
      "type": "hypothesis",
      "text": "If you were in Japan eating edamame, what would you be eating. Green Beans",
      "strength": 0.5
    },
    "H2": {
      "type": "hypothesis",
      "text": "If you were in Japan eating edamame, what would you be eating. Mung Beans",
      "strength": 0.5
    },
    "H3": {
      "type": "hypothesis",
      "text": "If you were in Japan eating edamame, what would you be eating. Soy",
      "strength": 0.749902562007873
    },
    "A4": {
      "type": "argument",
      "text": "Edamame is prepared with immature soybeans in their pods",
      "strength": 0.5
    },
    "A5": {
      "type": "argument",
      "text": "Edamame is soy and is classed as a major food allergen",
      "strength": 0.5
    }
  },
  "edges": [
    {
      "source": "A4",
      "target": "H3",
      "relation": "support"
    },
    {
      "source": "A5",
      "target": "H3",
      "relation": "support"
    }
  ]
}