{
  "nodes": {
    "H0": {
      "type": "hypothesis",
      "text": "Who were the first team to concede 100 goals in a season in the Premiership. Ipswich Town",
      "strength": 0.5
    },
    "H1": {
      "type": "hypothesis",
      "text": "Who were the first team to concede 100 goals in a season in the Premiership. Derby County",
      "strength": 0.5
    },
    "H2": {
      "type": "hypothesis",
      "text": "Who were the first team to concede 100 goals in a season in the Premiership. Sunderland",
      "strength": 0.5
    },
    "H3": {
      "type": "hypothesis",
      "text": "Who were the first team to concede 100 goals in a season in the Premiership. Swindon Town",
      "strength": 0.5999031730402274
    },
    "A4": {
      "type": "argument",
      "text": "Swindon Town conceded 100 goals in a season in the Premier League in 1993–94, a record that stood until Sheffield United broke it in 2024",
      "strength": 0.5
    }
  },
  "edges": [
    {
      "source": "A4",
      "target": "H3",
      "relation": "support"
    }
  ]
}