{
  "nodes": {
    "H0": {
      "type": "hypothesis",
      "text": "What should you cross for good luck. Toes",
      "strength": 0.5
    },
    "H1": {
      "type": "hypothesis",
      "text": "What should you cross for good luck. Arms",
      "strength": 0.5
    },
    "H2": {
      "type": "hypothesis",
      "text": "What should you cross for good luck. Legs",
      "strength": 0.5
    },
    "H3": {
      "type": "hypothesis",
      "text": "What should you cross for good luck. Fingers",
      "strength": 0.5
    }
  },
  "edges": []
}