{
  "nodes": {
    "H0": {
      "type": "hypothesis",
      "text": "Blood is the means by which traits are passed on from one generation to the next in living things.",
      "strength": 0.5
    },
    "H1": {
      "type": "hypothesis",
      "text": "Minerals are the substances transferred in living organisms to pass traits from one generation to the next.",
      "strength": 0.5
    },
    "H2": {
      "type": "hypothesis",
      "text": "Calories are transferred from one generation to the next in living things to pass on traits.",
      "strength": 0.5
    },
    "H3": {
      "type": "hypothesis",
      "text": "DNA is the material transferred in living things that passes traits from one generation to the next.",
      "strength": 0.749902562007873
    },
    "A4": {
      "type": "argument",
      "text": "DNA contains the genetic information that allows all forms of life to function, grow and reproduce.",
      "strength": 0.5
    },
    "A5": {
      "type": "argument",
      "text": "Transmission of genetic information in genes is achieved via complementary base pairing.",
      "strength": 0.5
    }
  },
  "edges": [
    {
      "source": "A4",
      "target": "H3",
      "relation": "support"
    },
    {
      "source": "A5",
      "target": "H3",
      "relation": "support"
    }
  ]
}