{
  "nodes": {
    "H0": {
      "type": "hypothesis",
      "text": "The nucleus is the part of a plant cell where photosynthesis occurs.",
      "strength": 0.5
    },
    "H1": {
      "type": "hypothesis",
      "text": "Chloroplast is the part of a plant cell where photosynthesis occurs.",
      "strength": 0.749902562007873
    },
    "H2": {
      "type": "hypothesis",
      "text": "Cell membrane is the part of a plant cell where photosynthesis occurs.",
      "strength": 0.5
    },
    "H3": {
      "type": "hypothesis",
      "text": "Cell wall is the part of a plant cell in which photosynthesis occurs.",
      "strength": 0.5
    },
    "A4": {
      "type": "argument",
      "text": "A chloroplast (KLOR-ə-plast, -⁠plahst) is a type of organelle known as a plastid that conducts photosynthesis mostly in plant and algal cells.",
      "strength": 0.5
    },
    "A5": {
      "type": "argument",
      "text": "Chloroplasts have a high concentration of chlorophyll pigments which capture the energy from sunlight and convert it to chemical energy and release oxygen.",
      "strength": 0.5
    }
  },
  "edges": [
    {
      "source": "A4",
      "target": "H1",
      "relation": "support"
    },
    {
      "source": "A5",
      "target": "H1",
      "relation": "support"
    }
  ]
}