{
  "nodes": {
    "H0": {
      "type": "hypothesis",
      "text": "Circulatory is the system in which peristalsis helps move nutrients through parts of the body by using wavelike contractions.",
      "strength": 0.5999088118033908
    },
    "H1": {
      "type": "hypothesis",
      "text": "Digestive is the system in which peristalsis, which helps move nutrients through parts of the body by using wavelike contractions, is used.",
      "strength": 0.5
    },
    "H2": {
      "type": "hypothesis",
      "text": "Endocrine is the system in which peristalsis helps move nutrients through parts of the body by using wavelike contractions.",
      "strength": 0.5
    },
    "H3": {
      "type": "hypothesis",
      "text": "The nervous system is the system in which peristalsis, which helps move nutrients through parts of the body by using wavelike contractions, is used.",
      "strength": 0.5999088118033908
    },
    "A4": {
      "type": "argument",
      "text": "The human lymphatic system has no central pump. Instead, lymph circulates through peristalsis in the lymph capillaries as well as valves in the capillaries, compression during contraction of adjacent skeletal muscle, and arterial pulsation.",
      "strength": 0.5
    },
    "A5": {
      "type": "argument",
      "text": "The process of peristalsis is controlled by the medulla oblongata.",
      "strength": 0.5
    }
  },
  "edges": [
    {
      "source": "A4",
      "target": "H0",
      "relation": "support"
    },
    {
      "source": "A5",
      "target": "H3",
      "relation": "support"
    }
  ]
}