{
  "nodes": {
    "H0": {
      "type": "hypothesis",
      "text": "Wave function is the type of function that Schrödinger’s approach uses three quantum numbers (n, l, and ml) to specify, each associated with a particular energy.",
      "strength": 0.25009174651106497
    },
    "H1": {
      "type": "hypothesis",
      "text": "Shift function is the type of function that Schrödinger’s approach uses three quantum numbers (n, l, and ml) to specify, which is associated with a particular energy.",
      "strength": 0.5
    },
    "H2": {
      "type": "hypothesis",
      "text": "Green function is the type of function that Schrödinger’s approach uses three quantum numbers (n, l, and ml) to specify, each associated with a particular energy.",
      "strength": 0.5
    },
    "H3": {
      "type": "hypothesis",
      "text": "Rush function is a function that Schrödinger’s approach uses the three quantum numbers (n, l, and ml) to specify, associating it with a particular energy.",
      "strength": 0.4000000585968386
    },
    "A4": {
      "type": "argument",
      "text": "The Schrödinger equation's solutions are wave functions, which are labeled by quantum numbers.",
      "strength": 0.5
    },
    "A5": {
      "type": "argument",
      "text": "The text does not mention 'shift', 'green', or 'rush' functions being used in Schrödinger’s approach.",
      "strength": 0.5
    },
    "A6": {
      "type": "argument",
      "text": "The text does not mention the use of three specific quantum numbers (n, l, and ml) in Schrödinger’s approach.",
      "strength": 0.5
    }
  },
  "edges": [
    {
      "source": "A4",
      "target": "H0",
      "relation": "attack"
    },
    {
      "source": "A5",
      "target": "H3",
      "relation": "attack"
    },
    {
      "source": "A6",
      "target": "H0",
      "relation": "attack"
    }
  ]
}