{
  "nodes": {
    "H0": {
      "type": "hypothesis",
      "text": "Preventive vaccinations are how you can prevent diseases such as whooping cough and flu.",
      "strength": 0.749902562007873
    },
    "H1": {
      "type": "hypothesis",
      "text": "Nutrition can prevent diseases such as whooping cough and flu.",
      "strength": 0.5
    },
    "H2": {
      "type": "hypothesis",
      "text": "Exercise can help prevent diseases such as whooping cough and flu.",
      "strength": 0.5
    },
    "H3": {
      "type": "hypothesis",
      "text": "Vacuuming is a way to prevent diseases such as whooping cough and flu.",
      "strength": 0.5
    },
    "A4": {
      "type": "argument",
      "text": "Vaccination is the most effective method of preventing infectious diseases",
      "strength": 0.5
    },
    "A5": {
      "type": "argument",
      "text": "In stimulating the body's adaptive immunity, they help prevent sickness from an infectious disease",
      "strength": 0.5
    }
  },
  "edges": [
    {
      "source": "A4",
      "target": "H0",
      "relation": "support"
    },
    {
      "source": "A5",
      "target": "H0",
      "relation": "support"
    }
  ]
}