{
  "nodes": {
    "H0": {
      "type": "hypothesis",
      "text": "Vaginal secretions are released to lubricate the vagina to facilitate intercourse.",
      "strength": 0.749902562007873
    },
    "H1": {
      "type": "hypothesis",
      "text": "Urine is released to lubricate the vagina to facilitate intercourse.",
      "strength": 0.5
    },
    "H2": {
      "type": "hypothesis",
      "text": "Blood is released to lubricate the vagina to facilitate intercourse.",
      "strength": 0.5
    },
    "H3": {
      "type": "hypothesis",
      "text": "Semen is released to lubricate the vagina to facilitate intercourse.",
      "strength": 0.5
    },
    "A4": {
      "type": "argument",
      "text": "Plasma from the vaginal walls due to vascular engorgement is considered to be the chief lubrication source, and the Bartholin's glands, located slightly below and to the left and right of the introitus (vaginal opening), also secrete mucus to augment vaginal wall secretions.",
      "strength": 0.5
    },
    "A5": {
      "type": "argument",
      "text": "The human vagina is serviced by nerves that respond to vasoactive intestinal polypeptide (VIP). As a result, VIP induces an increase in vaginal blood flow accompanied by an increase in vaginal lubrication.",
      "strength": 0.5
    }
  },
  "edges": [
    {
      "source": "A4",
      "target": "H0",
      "relation": "support"
    },
    {
      "source": "A5",
      "target": "H0",
      "relation": "support"
    }
  ]
}