{
  "nodes": {
    "H0": {
      "type": "hypothesis",
      "text": "Neurotransmitters are the objects released at a synapse to carry a nerve impulse from one neuron to the next.",
      "strength": 0.749902562007873
    },
    "H1": {
      "type": "hypothesis",
      "text": "Viruses are the objects released at a synapse to carry a nerve impulse from one neuron to the next.",
      "strength": 0.5
    },
    "H2": {
      "type": "hypothesis",
      "text": "Receptors are the objects released at a synapse to carry a nerve impulse from one neuron to the next.",
      "strength": 0.5
    },
    "H3": {
      "type": "hypothesis",
      "text": "Microorganisms are the objects released at a synapse to carry a nerve impulse from one neuron to the next.",
      "strength": 0.5
    },
    "A4": {
      "type": "argument",
      "text": "Neurotransmitters are tiny signal molecules stored in membrane-enclosed synaptic vesicles and released via exocytosis.",
      "strength": 0.5
    },
    "A5": {
      "type": "argument",
      "text": "Chemical synapses communicate through neurotransmitters released from the presynaptic neuron into the synaptic cleft.",
      "strength": 0.5
    }
  },
  "edges": [
    {
      "source": "A4",
      "target": "H0",
      "relation": "support"
    },
    {
      "source": "A5",
      "target": "H0",
      "relation": "support"
    }
  ]
}