{
  "nodes": {
    "H0": {
      "type": "hypothesis",
      "text": "Skin is where nerve cells that sense touch are mainly found.",
      "strength": 0.749902562007873
    },
    "H1": {
      "type": "hypothesis",
      "text": "Stomach is the main location where nerve cells that sense touch are found.",
      "strength": 0.5
    },
    "H2": {
      "type": "hypothesis",
      "text": "Brain is the main location where nerve cells that sense touch are found.",
      "strength": 0.5
    },
    "H3": {
      "type": "hypothesis",
      "text": "Lungs are the main site where nerve cells that sense touch are found.",
      "strength": 0.5
    },
    "A4": {
      "type": "argument",
      "text": "It harbors many mechanoreceptors (nerve endings) that provide the sense of touch and heat through nociceptors and thermoreceptors.",
      "strength": 0.5
    },
    "A5": {
      "type": "argument",
      "text": "contains a variety of nerve endings that jump to heat and cold, touch, pressure, vibration, and tissue injury",
      "strength": 0.5
    }
  },
  "edges": [
    {
      "source": "A4",
      "target": "H0",
      "relation": "support"
    },
    {
      "source": "A5",
      "target": "H0",
      "relation": "support"
    }
  ]
}