{
  "nodes": {
    "H0": {
      "type": "hypothesis",
      "text": "In which country will you find the Kremesta Dam. Greece",
      "strength": 0.749902562007873
    },
    "H1": {
      "type": "hypothesis",
      "text": "In which country will you find the Kremesta Dam. Turkey",
      "strength": 0.5
    },
    "H2": {
      "type": "hypothesis",
      "text": "In which country will you find the Kremesta Dam. Bulgaria",
      "strength": 0.5
    },
    "H3": {
      "type": "hypothesis",
      "text": "In which country will you find the Kremesta Dam. Elás",
      "strength": 0.5
    },
    "A6": {
      "type": "argument",
      "text": "The dam powers electricity for the western part of Greece and the central part.",
      "strength": 0.5
    },
    "A7": {
      "type": "argument",
      "text": "The Kremasta Dam in the Aitoloacarnania-Evrytania boundary was under construction.",
      "strength": 0.5
    }
  },
  "edges": [
    {
      "source": "A6",
      "target": "H0",
      "relation": "support"
    },
    {
      "source": "A7",
      "target": "H0",
      "relation": "support"
    }
  ]
}