{
  "nodes": {
    "H0": {
      "type": "hypothesis",
      "text": "who was king after leonidas died. Pausanias",
      "strength": 0.5
    },
    "H1": {
      "type": "hypothesis",
      "text": "who was king after leonidas died. Agesilaus II",
      "strength": 0.5
    },
    "H2": {
      "type": "hypothesis",
      "text": "who was king after leonidas died. Demaratus",
      "strength": 0.5
    },
    "H3": {
      "type": "hypothesis",
      "text": "who was king after leonidas died. Pleistarchus",
      "strength": 0.749902562007873
    },
    "A4": {
      "type": "argument",
      "text": "Pleistarchus was the Agiad King of Sparta from 480 to 458 BC",
      "strength": 0.5
    },
    "A5": {
      "type": "argument",
      "text": "Pleistarchus' father King Leonidas perished in 480 BC at the Battle of Thermopylae",
      "strength": 0.5
    }
  },
  "edges": [
    {
      "source": "A4",
      "target": "H3",
      "relation": "support"
    },
    {
      "source": "A5",
      "target": "H3",
      "relation": "support"
    }
  ]
}