{
  "nodes": {
    "H0": {
      "type": "hypothesis",
      "text": "The word apostle is derived from Greek 'apostolos' meaning. Ambassador",
      "strength": 0.5999050903424904
    },
    "H1": {
      "type": "hypothesis",
      "text": "The word apostle is derived from Greek 'apostolos' meaning. Envoy",
      "strength": 0.5
    },
    "H2": {
      "type": "hypothesis",
      "text": "The word apostle is derived from Greek 'apostolos' meaning. Delegate",
      "strength": 0.5
    },
    "H3": {
      "type": "hypothesis",
      "text": "The word apostle is derived from Greek 'apostolos' meaning. Messenger",
      "strength": 0.5999050903424904
    },
    "A4": {
      "type": "argument",
      "text": "The word apostle is translated as 'messenger' in English.",
      "strength": 0.5
    },
    "A5": {
      "type": "argument",
      "text": "The word apostle is translated as 'ambassador' in English.",
      "strength": 0.5
    }
  },
  "edges": [
    {
      "source": "A4",
      "target": "H3",
      "relation": "support"
    },
    {
      "source": "A5",
      "target": "H0",
      "relation": "support"
    }
  ]
}