{
  "nodes": {
    "H0": {
      "type": "hypothesis",
      "text": "what tv shows did shawnee smith play in. Anger Management",
      "strength": 0.5
    },
    "H1": {
      "type": "hypothesis",
      "text": "what tv shows did shawnee smith play in. The Tom Show",
      "strength": 0.5
    },
    "H2": {
      "type": "hypothesis",
      "text": "what tv shows did shawnee smith play in. Saw",
      "strength": 0.5
    },
    "H3": {
      "type": "hypothesis",
      "text": "what tv shows did shawnee smith play in. Becker",
      "strength": 0.5
    }
  },
  "edges": []
}