{
  "nodes": {
    "H0": {
      "type": "hypothesis",
      "text": "Leicester City FC's owners are (at 2016) what nationality. Chinese",
      "strength": 0.5
    },
    "H1": {
      "type": "hypothesis",
      "text": "Leicester City FC's owners are (at 2016) what nationality. Indian",
      "strength": 0.5
    },
    "H2": {
      "type": "hypothesis",
      "text": "Leicester City FC's owners are (at 2016) what nationality. Malaysian",
      "strength": 0.5
    },
    "H3": {
      "type": "hypothesis",
      "text": "Leicester City FC's owners are (at 2016) what nationality. Siam",
      "strength": 0.5
    }
  },
  "edges": []
}