{
  "nodes": {
    "H0": {
      "type": "hypothesis",
      "text": "What name is given to the hot, molten rock found under the surface of the earth. Lava",
      "strength": 0.40009682695977267
    },
    "H1": {
      "type": "hypothesis",
      "text": "What name is given to the hot, molten rock found under the surface of the earth. Geoma",
      "strength": 0.5
    },
    "H2": {
      "type": "hypothesis",
      "text": "What name is given to the hot, molten rock found under the surface of the earth. Pyrope",
      "strength": 0.5
    },
    "H3": {
      "type": "hypothesis",
      "text": "What name is given to the hot, molten rock found under the surface of the earth. MAGMA",
      "strength": 0.5999031730402274
    },
    "A4": {
      "type": "argument",
      "text": "Magma (from Ancient Greek μάγμα (mágma) 'thick unguent') is the molten or semi-molten natural material from which all igneous rocks are formed. Magma ... is found beneath the surface of the Earth",
      "strength": 0.5
    },
    "A5": {
      "type": "argument",
      "text": "Magma (sometimes colloquially but incorrectly referred to as lava)",
      "strength": 0.5
    }
  },
  "edges": [
    {
      "source": "A4",
      "target": "H3",
      "relation": "support"
    },
    {
      "source": "A5",
      "target": "H0",
      "relation": "attack"
    }
  ]
}