{
  "nodes": {
    "H0": {
      "type": "hypothesis",
      "text": "What is the name given to the largest bee in a hive. Monarcha",
      "strength": 0.5
    },
    "H1": {
      "type": "hypothesis",
      "text": "What is the name given to the largest bee in a hive. Apiana",
      "strength": 0.5
    },
    "H2": {
      "type": "hypothesis",
      "text": "What is the name given to the largest bee in a hive. Dominula",
      "strength": 0.5
    },
    "H3": {
      "type": "hypothesis",
      "text": "What is the name given to the largest bee in a hive. Quene",
      "strength": 0.5
    }
  },
  "edges": []
}