{
  "nodes": {
    "H0": {
      "type": "hypothesis",
      "text": "Which monastic order, founded in 529 AD, was based at a monastery at Monte Cassino, Italy, until it was sacked in 580, when the monks fled to Rome and then spread throughout Europe. Benedictines",
      "strength": 0.749902562007873
    },
    "H1": {
      "type": "hypothesis",
      "text": "Which monastic order, founded in 529 AD, was based at a monastery at Monte Cassino, Italy, until it was sacked in 580, when the monks fled to Rome and then spread throughout Europe. Franciscans",
      "strength": 0.5
    },
    "H2": {
      "type": "hypothesis",
      "text": "Which monastic order, founded in 529 AD, was based at a monastery at Monte Cassino, Italy, until it was sacked in 580, when the monks fled to Rome and then spread throughout Europe. Dominicans",
      "strength": 0.5
    },
    "H3": {
      "type": "hypothesis",
      "text": "Which monastic order, founded in 529 AD, was based at a monastery at Monte Cassino, Italy, until it was sacked in 580, when the monks fled to Rome and then spread throughout Europe. O.S.B.",
      "strength": 0.5
    },
    "A4": {
      "type": "argument",
      "text": "The Abbey of Monte Cassino was founded by Benedict of Nursia c. 529, and it was sacked by the Lombards about the year 580, prompting the monks to flee to Rome.",
      "strength": 0.5
    },
    "A5": {
      "type": "argument",
      "text": "The Benedictine monastic order is the oldest of all the religious orders in the Latin Church, initiated in 529.",
      "strength": 0.5
    }
  },
  "edges": [
    {
      "source": "A4",
      "target": "H0",
      "relation": "support"
    },
    {
      "source": "A5",
      "target": "H0",
      "relation": "support"
    }
  ]
}