{
  "nodes": {
    "H0": {
      "type": "hypothesis",
      "text": "What was said to have been guarded by the Fisher King. Holy Scepter",
      "strength": 0.5
    },
    "H1": {
      "type": "hypothesis",
      "text": "What was said to have been guarded by the Fisher King. Sacred Chalice",
      "strength": 0.5
    },
    "H2": {
      "type": "hypothesis",
      "text": "What was said to have been guarded by the Fisher King. Magical Amulet",
      "strength": 0.5
    },
    "H3": {
      "type": "hypothesis",
      "text": "What was said to have been guarded by the Fisher King. Grail",
      "strength": 0.5
    },
    "A4": {
      "type": "argument",
      "text": "The Grail was kept safe at the castle of Munsalvaesche, entrusted to Titurel, the first Grail King.",
      "strength": 0.5
    },
    "A5": {
      "type": "argument",
      "text": "In the story of Perceval, the Grail was carried by a girl in the procession, and the Fisher King was the one who required healing through its power.",
      "strength": 0.5
    }
  },
  "edges": [
    {
      "source": "A4",
      "target": "H3",
      "relation": "attack"
    },
    {
      "source": "A5",
      "target": "H3",
      "relation": "support"
    }
  ]
}