{
  "nodes": {
    "H0": {
      "type": "hypothesis",
      "text": "when did the democratic party change its name. The 1840s",
      "strength": 0.5000892985607654
    },
    "H1": {
      "type": "hypothesis",
      "text": "when did the democratic party change its name. The 1850s",
      "strength": 0.5
    },
    "H2": {
      "type": "hypothesis",
      "text": "when did the democratic party change its name. The 1820s",
      "strength": 0.5
    },
    "H3": {
      "type": "hypothesis",
      "text": "when did the democratic party change its name. the 1830s",
      "strength": 0.5
    },
    "A4": {
      "type": "argument",
      "text": "the name 'Democratic Party' was eventually settled upon and became the official name in 1844",
      "strength": 0.5
    },
    "A5": {
      "type": "argument",
      "text": "Address to the Democratic Republican Electors of the State of New York (1840). Published before the formation of party national committees.",
      "strength": 0.5
    }
  },
  "edges": [
    {
      "source": "A4",
      "target": "H0",
      "relation": "support"
    },
    {
      "source": "A5",
      "target": "H0",
      "relation": "attack"
    }
  ]
}