{
  "nodes": {
    "H0": {
      "type": "hypothesis",
      "text": "who sang from russia with love james bond. Tom Jones",
      "strength": 0.5
    },
    "H1": {
      "type": "hypothesis",
      "text": "who sang from russia with love james bond. Frank Sinatra",
      "strength": 0.5
    },
    "H2": {
      "type": "hypothesis",
      "text": "who sang from russia with love james bond. Dean Martin",
      "strength": 0.5
    },
    "H3": {
      "type": "hypothesis",
      "text": "who sang from russia with love james bond. Matt Monro",
      "strength": 0.5999031730402274
    },
    "A4": {
      "type": "argument",
      "text": "The theme song was composed by Lionel Bart of Oliver! fame and sung by Matt Monro.",
      "strength": 0.5
    }
  },
  "edges": [
    {
      "source": "A4",
      "target": "H3",
      "relation": "support"
    }
  ]
}