{
  "nodes": {
    "H0": {
      "type": "hypothesis",
      "text": "What kind of bird is the Ugly Duckling. Goose",
      "strength": 0.5
    },
    "H1": {
      "type": "hypothesis",
      "text": "What kind of bird is the Ugly Duckling. Pochard",
      "strength": 0.5
    },
    "H2": {
      "type": "hypothesis",
      "text": "What kind of bird is the Ugly Duckling. Merganser",
      "strength": 0.5
    },
    "H3": {
      "type": "hypothesis",
      "text": "What kind of bird is the Ugly Duckling. Swan",
      "strength": 0.5
    }
  },
  "edges": []
}