{
  "nodes": {
    "H0": {
      "type": "hypothesis",
      "text": "Who was the first person in the bible to get drunk. Lot",
      "strength": 0.5999031730402274
    },
    "H1": {
      "type": "hypothesis",
      "text": "Who was the first person in the bible to get drunk. Nabal",
      "strength": 0.5
    },
    "H2": {
      "type": "hypothesis",
      "text": "Who was the first person in the bible to get drunk. Esau",
      "strength": 0.5
    },
    "H3": {
      "type": "hypothesis",
      "text": "Who was the first person in the bible to get drunk. Noah",
      "strength": 0.5
    },
    "A4": {
      "type": "argument",
      "text": "Lot's eldest daughter got him drunk and had sex with him without his knowledge.",
      "strength": 0.5
    }
  },
  "edges": [
    {
      "source": "A4",
      "target": "H0",
      "relation": "support"
    }
  ]
}