{
  "nodes": {
    "H0": {
      "type": "hypothesis",
      "text": "Which city in the USA suffered a huge fire in 1871 allegedly started by a cow. Chicago",
      "strength": 0.749902562007873
    },
    "H1": {
      "type": "hypothesis",
      "text": "Which city in the USA suffered a huge fire in 1871 allegedly started by a cow. New York City",
      "strength": 0.5
    },
    "H2": {
      "type": "hypothesis",
      "text": "Which city in the USA suffered a huge fire in 1871 allegedly started by a cow. Boston",
      "strength": 0.5
    },
    "H3": {
      "type": "hypothesis",
      "text": "Which city in the USA suffered a huge fire in 1871 allegedly started by a cow. USCHI",
      "strength": 0.5
    },
    "A4": {
      "type": "argument",
      "text": "The Great Chicago Fire occurred in Chicago, Illinois, during October 8–10, 1871.",
      "strength": 0.5
    },
    "A5": {
      "type": "argument",
      "text": "The most popular tale blames Mrs. O'Leary's cow, which allegedly knocked over a lantern.",
      "strength": 0.5
    }
  },
  "edges": [
    {
      "source": "A4",
      "target": "H0",
      "relation": "support"
    },
    {
      "source": "A5",
      "target": "H0",
      "relation": "support"
    }
  ]
}