{
  "nodes": {
    "H0": {
      "type": "hypothesis",
      "text": "After Harold McMillan who was Britain's next Prime Minister. Alec Douglas-Home's brother",
      "strength": 0.5
    },
    "H1": {
      "type": "hypothesis",
      "text": "After Harold McMillan who was Britain's next Prime Minister. Reginald Maudling",
      "strength": 0.5
    },
    "H2": {
      "type": "hypothesis",
      "text": "After Harold McMillan who was Britain's next Prime Minister. Rab Butler",
      "strength": 0.5
    },
    "H3": {
      "type": "hypothesis",
      "text": "After Harold McMillan who was Britain's next Prime Minister. Douglas-home",
      "strength": 0.5
    }
  },
  "edges": []
}